semantic_version_check/__init__.py
semantic_version_check/__main__.py
semantic_version_check/cli.py
semantic_version_check/main.py
semantic_version_check/py.typed
semantic_version_check-1.0.2.dist-info/METADATA
semantic_version_check-1.0.2.dist-info/WHEEL
semantic_version_check-1.0.2.dist-info/entry_points.txt
semantic_version_check-1.0.2.dist-info/top_level.txt
semantic_version_check-1.0.2.dist-info/RECORD
