Metadata-Version: 2.1
Name: semantic-version-check
Version: 1.0.2
Summary: Check if a 'version' is a valid Semantic Version.
Home-page: https://github.com/boromir674/semantic-version-check
Download-URL: https://github.com/boromir674/semantic-version-check/archive/v1.0.2.tar.gz
Author: Konstantinos Lampridis
Author-email: k.lampridis@hotmail.com
License: AGPLv3
Project-URL: Bug Tracker, https://github.com/semantic-version-check/issues
Project-URL: CI: Github Actions, https://github.com/boromir674/semantic-version-check/actions
Project-URL: Documentation, https://semantic-version-check.readthedocs.io/
Project-URL: Source Code, https://github.com/boromir674/semantic-version-check
Project-URL: Changelog, https://github.com/boromir674/semantic-version-check/blob/master/CHANGELOG.rst
Project-URL: Code of Conduct, https://github.com/boromir674/semantic-version-check/blob/master/CONTRIBUTING.rst
Keywords: python package
Platform: Linux
Platform: Darwin
Classifier: Development Status :: 5 - Production/Stable
Classifier: Intended Audience :: Developers
Classifier: Intended Audience :: End Users/Desktop
Classifier: Intended Audience :: Science/Research
Classifier: License :: OSI Approved :: GNU Affero General Public License v3
Classifier: Natural Language :: English
Classifier: Operating System :: Unix
Classifier: Programming Language :: Python
Classifier: Programming Language :: Python :: 3.6
Classifier: Programming Language :: Python :: 3.7
Classifier: Programming Language :: Python :: 3.8
Classifier: Programming Language :: Python :: 3.9
Classifier: Programming Language :: Python :: 3.10
Classifier: Topic :: Software Development
Classifier: Topic :: Software Development :: Libraries :: Python Modules
Classifier: Topic :: System :: Software Distribution
Classifier: Typing :: Typed
Requires-Python: >=3.6
Provides-Extra: docs
Requires-Dist: sphinx (~=4.0) ; extra == 'docs'
Requires-Dist: sphinx-argparse-cli (>=1.5) ; extra == 'docs'
Requires-Dist: sphinx-autodoc-typehints (>=1.10) ; extra == 'docs'
Requires-Dist: sphinx-rtd-theme (==0.5.0) ; extra == 'docs'
Requires-Dist: sphinxcontrib-spelling ; extra == 'docs'
Provides-Extra: test
Requires-Dist: pytest (>=6.2.4) ; extra == 'test'
Requires-Dist: pytest-cov (>=2.12) ; extra == 'test'
Requires-Dist: pytest-click (~=1.1.0) ; extra == 'test'
Requires-Dist: pytest-xdist (>=1.34) ; extra == 'test'
Provides-Extra: typing
Requires-Dist: mypy ; extra == 'typing'
Requires-Dist: pytest (>=6.2.4) ; extra == 'typing'
Requires-Dist: pytest-click (~=1.1.0) ; extra == 'typing'
